jb_news/__init__.py
jb_news/news.py
jb_news-2.3.1.dist-info/METADATA
jb_news-2.3.1.dist-info/WHEEL
jb_news-2.3.1.dist-info/top_level.txt
jb_news-2.3.1.dist-info/RECORD
