Metadata-Version: 2.1
Name: jb-news
Version: 2.3.1
Summary: A comprehensive wrapper for JBlanked's News API, leveraging OpenAI, Machine Learning, and MQL5's Calendar.
Home-page: https://jblanked.com/news/api/docs/
Author: JBlanked
License: MIT
Requires-Dist: requests
